alibabacloud_dts20190901/__init__.py
alibabacloud_dts20190901/client.py
alibabacloud_dts20190901/models.py
alibabacloud_dts20190901_py2-1.0.0.dist-info/LICENSE
alibabacloud_dts20190901_py2-1.0.0.dist-info/METADATA
alibabacloud_dts20190901_py2-1.0.0.dist-info/WHEEL
alibabacloud_dts20190901_py2-1.0.0.dist-info/top_level.txt
alibabacloud_dts20190901_py2-1.0.0.dist-info/RECORD
